[
	{
		"image_url" : "/static/img/01.jpg",
		"image_width" : 1028,
		"image_height" : 1440,
		"video_id" : "VugtWhufJhI"
	},
	{
		"image_url" : "/static/img/02.jpg",
		"image_width" : 600,
		"image_height" : 447,
		"video_id" : "IkagLuxAV4o"
	},
	{
		"image_url" : "/static/img/03.jpg",
		"image_width" : 546,
		"image_height" : 639,
		"video_id" : "iTH-LyV7LDw"
	},
	{
		"image_url" : "/static/img/04.jpg",
		"image_width" : 450,
		"image_height" : 330,
		"video_id" : "zfdITZ0DQns"
	},
	{
		"image_url" : "/static/img/05.jpg",
		"image_width" : 1920,
		"image_height" : 1080,
		"video_id" : "Vp8yqdGBLvU"
	},
	{
		"image_url" : "/static/img/06.jpg",
		"image_width" : 400,
		"image_height" : 400,
		"video_id" : "1MYZaEBB7iw"
	},
	{
		"image_url" : "/static/img/07.jpg",
		"image_width" : 324,
		"image_height" : 324,
		"video_id" : "pYH0bBPgyhM"
	},
	{
		"image_url" : "/static/img/08.jpg",
		"image_width" : 800,
		"image_height" : 600,
		"video_id" : "GUrzBKVvvDY"
	},
	{
		"image_url" : "/static/img/09.jpg",
		"image_width" : 362,
		"image_height" : 500,
		"video_id" : "Qg3Lih9PTBM"
	},
	{
		"image_url" : "/static/img/10.jpg",
		"image_width" : 670,
		"image_height" : 380,
		"video_id" : "f71VqFgwPy4"
	},
	{
		"image_url" : "/static/img/11.jpg",
		"image_width" : 1024,
		"image_height" : 692,
		"video_id" : "3QRy-PEgbls"
	},
	{
		"image_url" : "/static/img/12.jpg",
		"image_width" : 470,
		"image_height" : 470,
		"video_id" : "z9Q64gLVxJg"
	},
	{
		"image_url" : "/static/img/13.jpg",
		"image_width" : 253,
		"image_height" : 356,
		"video_id" : "paNyqN2qxJU"
	}
]
